cksplinter/__init__.py
cksplinter/browser.py
cksplinter/cookie_manager.py
cksplinter/element_list.py
cksplinter/exceptions.py
cksplinter/meta.py
cksplinter/driver/__init__.py
cksplinter/driver/djangoclient.py
cksplinter/driver/element_present.py
cksplinter/driver/find_links.py
cksplinter/driver/flaskclient.py
cksplinter/driver/lxmldriver.py
cksplinter/driver/xpath_utils.py
cksplinter/driver/zopetestbrowser.py
cksplinter/driver/webdriver/__init__.py
cksplinter/driver/webdriver/chrome.py
cksplinter/driver/webdriver/cookie_manager.py
cksplinter/driver/webdriver/edge.py
cksplinter/driver/webdriver/firefox.py
cksplinter/driver/webdriver/remote.py
cksplinter/driver/webdriver/remote_connection.py
cksplinter/request_handler/__init__.py
cksplinter/request_handler/status_code.py
splinter/__init__.py
splinter/browser.py
splinter/cookie_manager.py
splinter/element_list.py
splinter/exceptions.py
splinter/meta.py
splinter/driver/__init__.py
splinter/driver/djangoclient.py
splinter/driver/element_present.py
splinter/driver/find_links.py
splinter/driver/flaskclient.py
splinter/driver/lxmldriver.py
splinter/driver/xpath_utils.py
splinter/driver/zopetestbrowser.py
splinter/driver/webdriver/__init__.py
splinter/driver/webdriver/chrome.py
splinter/driver/webdriver/cookie_manager.py
splinter/driver/webdriver/edge.py
splinter/driver/webdriver/firefox.py
splinter/driver/webdriver/remote.py
splinter/driver/webdriver/remote_connection.py
splinter/request_handler/__init__.py
splinter/request_handler/status_code.py
cksplinter-0.17.3.dist-info/AUTHORS
cksplinter-0.17.3.dist-info/LICENSE
cksplinter-0.17.3.dist-info/METADATA
cksplinter-0.17.3.dist-info/WHEEL
cksplinter-0.17.3.dist-info/top_level.txt
cksplinter-0.17.3.dist-info/RECORD
