Metadata-Version: 2.1
Name: cksplinter
Version: 0.17.3
Summary: browser abstraction for web acceptance testing
Home-page: https://github.com/cobrateam/splinter
Author: CobraTeam
Author-email: andrewsmedina@gmail.com
License: BSD
Project-URL: Documentation, https://splinter.readthedocs.io/
Project-URL: Changelog, https://github.com/cobrateam/splinter/tree/master/docs/news
Project-URL: Source, https://github.com/cobrateam/splinter/
Project-URL: Tracker, https://github.com/cobrateam/splinter/issues
Platform: UNKNOWN
Classifier: License :: OSI Approved :: BSD License
Classifier: Programming Language :: Python :: 3
Classifier: Programming Language :: Python :: 3.6
Classifier: Programming Language :: Python :: 3.7
Classifier: Programming Language :: Python :: 3.8
Classifier: Programming Language :: Python :: 3.9
License-File: LICENSE
License-File: AUTHORS
Provides-Extra: django
Requires-Dist: Django (>=2.0.6) ; extra == 'django'
Requires-Dist: lxml (>=4.2.4) ; extra == 'django'
Requires-Dist: cssselect ; extra == 'django'
Provides-Extra: edge
Requires-Dist: msedge-selenium-tools ; extra == 'edge'
Provides-Extra: flask
Requires-Dist: Flask (>=2.0.2) ; extra == 'flask'
Requires-Dist: lxml (>=4.2.4) ; extra == 'flask'
Requires-Dist: cssselect ; extra == 'flask'
Provides-Extra: selenium3
Requires-Dist: selenium (<4.0,>=3.141.0) ; extra == 'selenium3'
Provides-Extra: selenium4
Requires-Dist: selenium (<5.0,>=4.1.0) ; extra == 'selenium4'
Provides-Extra: zope.testbrowser
Requires-Dist: zope.testbrowser (>=5.5.1) ; extra == 'zope.testbrowser'
Requires-Dist: lxml (>=4.2.4) ; extra == 'zope.testbrowser'
Requires-Dist: cssselect ; extra == 'zope.testbrowser'
